gordo/__init__.py
gordo/_version.py
gordo/builder/__init__.py
gordo/builder/build_model.py
gordo/builder/local_build.py
gordo/builder/mlflow_utils.py
gordo/cli/__init__.py
gordo/cli/cli.py
gordo/cli/client.py
gordo/cli/custom_types.py
gordo/cli/workflow_generator.py
gordo/client/__init__.py
gordo/client/client.py
gordo/client/forwarders.py
gordo/client/io.py
gordo/client/utils.py
gordo/machine/__init__.py
gordo/machine/machine.py
gordo/machine/validators.py
gordo/machine/dataset/__init__.py
gordo/machine/dataset/base.py
gordo/machine/dataset/dataset.py
gordo/machine/dataset/datasets.py
gordo/machine/dataset/filter_rows.py
gordo/machine/dataset/sensor_tag.py
gordo/machine/dataset/data_provider/__init__.py
gordo/machine/dataset/data_provider/azure_utils.py
gordo/machine/dataset/data_provider/base.py
gordo/machine/dataset/data_provider/iroc_reader.py
gordo/machine/dataset/data_provider/ncs_reader.py
gordo/machine/dataset/data_provider/providers.py
gordo/machine/model/__init__.py
gordo/machine/model/base.py
gordo/machine/model/models.py
gordo/machine/model/register.py
gordo/machine/model/utils.py
gordo/machine/model/anomaly/__init__.py
gordo/machine/model/anomaly/base.py
gordo/machine/model/anomaly/diff.py
gordo/machine/model/factories/__init__.py
gordo/machine/model/factories/feedforward_autoencoder.py
gordo/machine/model/factories/lstm_autoencoder.py
gordo/machine/model/factories/utils.py
gordo/machine/model/transformer_funcs/__init__.py
gordo/machine/model/transformer_funcs/general.py
gordo/machine/model/transformers/__init__.py
gordo/machine/model/transformers/imputer.py
gordo/serializer/__init__.py
gordo/serializer/pipeline_from_definition.py
gordo/serializer/pipeline_into_definition.py
gordo/serializer/serializer.py
gordo/server/__init__.py
gordo/server/model_io.py
gordo/server/rest_api.py
gordo/server/server.py
gordo/server/utils.py
gordo/server/views/__init__.py
gordo/server/views/anomaly.py
gordo/server/views/base.py
gordo/util/__init__.py
gordo_components-0.47.0.dist-info/LICENSE
gordo_components-0.47.0.dist-info/METADATA
gordo_components-0.47.0.dist-info/WHEEL
gordo_components-0.47.0.dist-info/entry_points.txt
gordo_components-0.47.0.dist-info/top_level.txt
gordo_components-0.47.0.dist-info/zip-safe
gordo_components-0.47.0.dist-info/RECORD
